[
  {
    "model": "Auth_LDAP.Jobs",
    "pk": 1,
    "fields": {
      "name": "Руководитель",
      "sortBy": 1,
      "unique": "руководитель",
      "RAD_job": "Руководителя",
      "DAT_job": "Руководителю"
    }
  },
  {
    "model": "Auth_LDAP.Jobs",
    "pk": 2,
    "fields": {
      "name": "Заместитель руководителя",
      "sortBy": 2,
      "unique": "заместительруководителя",
      "RAD_job": "Заместителя руководителя",
      "DAT_job": "Заместителю руководителя"
    }
  },
  {
    "model": "Auth_LDAP.Jobs",
    "pk": 3,
    "fields": {
      "name": "ВРИО Заместителя руководителя",
      "sortBy": 3,
      "unique": "вриозаместителяруководителя",
      "RAD_job": "ВРИО Заместителя руководителя",
      "DAT_job": "ВРИО Заместителю руководителя"
    }
  },
  {
    "model": "Auth_LDAP.Jobs",
    "pk": 4,
    "fields": {
      "name": "Помощник руководителя",
      "sortBy": 4,
      "unique": "помощникруководителя",
      "RAD_job": "Помощника руководителя",
      "DAT_job": "Помощнику руководителя"
    }
  },
  {
    "model": "Auth_LDAP.Jobs",
    "pk": 5,
    "fields": {
      "name": "Начальник отдела",
      "sortBy": 5,
      "unique": "начальникотдела",
      "RAD_job": "Начальника отдела",
      "DAT_job": "Начальнику отдела"
    }
  },
  {
    "model": "Auth_LDAP.Jobs",
    "pk": 6,
    "fields": {
      "name": "Заместитель начальника отдела",
      "sortBy": 6,
      "unique": "заместительначальникаотдела",
      "RAD_job": "Заместителя начальника отдела",
      "DAT_job": "Заместителю начальника отдела"
    }
  },
  {
    "model": "Auth_LDAP.Jobs",
    "pk": 7,
    "fields": {
      "name": "Заместитель начальника",
      "sortBy": 7,
      "unique": "заместительначальника",
      "RAD_job": "Заместителя начальника",
      "DAT_job": "Заместителю начальника"
    }
  },
  {
    "model": "Auth_LDAP.Jobs",
    "pk": 8,
    "fields": {
      "name": "ВРИО Начальника отдела",
      "sortBy": 8,
      "unique": "врионачальникаотдела",
      "RAD_job": "ВРИО Начальника отдела",
      "DAT_job": "ВРИО Начальнику отдела"
    }
  },
  {
    "model": "Auth_LDAP.Jobs",
    "pk": 9,
    "fields": {
      "name": "Главный казначей",
      "sortBy": 9,
      "unique": "главныйказначей",
      "RAD_job": "Главного казначея",
      "DAT_job": "Главному казначею"
    }
  },
  {
    "model": "Auth_LDAP.Jobs",
    "pk": 10,
    "fields": {
      "name": "Старший казначей",
      "sortBy": 10,
      "unique": "старшийказначей",
      "RAD_job": "Старшего казначея",
      "DAT_job": "Старшему казначею"
    }
  },
  {
    "model": "Auth_LDAP.Jobs",
    "pk": 11,
    "fields": {
      "name": "Казначей",
      "sortBy": 11,
      "unique": "казначей",
      "RAD_job": "Казначея",
      "DAT_job": "Казначею"
    }
  },
  {
    "model": "Auth_LDAP.Jobs",
    "pk": 12,
    "fields": {
      "name": "Главный специалист - эксперт",
      "sortBy": 12,
      "unique": "главныйспециалистэксперт",
      "RAD_job": "Главного специалиста - эксперта",
      "DAT_job": "Главному специалисту - эксперту"
    }
  },
  {
    "model": "Auth_LDAP.Jobs",
    "pk": 13,
    "fields": {
      "name": "Ведущий специалист - эксперт",
      "sortBy": 13,
      "unique": "ведущийспециалистэксперт",
      "RAD_job": "Ведущего специалиста - эксперта",
      "DAT_job": "Ведущему специалисту - эксперту"
    }
  },
  {
    "model": "Auth_LDAP.Jobs",
    "pk": 14,
    "fields": {
      "name": "Специалист - эксперт",
      "sortBy": 14,
      "unique": "специалистэксперт",
      "RAD_job": "Специалиста - эксперта",
      "DAT_job": "Специалисту - эксперту"
    }
  },
  {
    "model": "Auth_LDAP.Jobs",
    "pk": 15,
    "fields": {
      "name": "Старший специалист 1 разряда",
      "sortBy": 15,
      "unique": "старшийспециалист1разряда",
      "RAD_job": "Старшего специалиста 1 разряда",
      "DAT_job": "Старшему специалисту 1 разряда"
    }
  },
  {
    "model": "Auth_LDAP.Jobs",
    "pk": 16,
    "fields": {
      "name": "Старший специалист 3 разряда",
      "sortBy": 16,
      "unique": "старшийспециалист3разряда",
      "RAD_job": "Старшего специалиста 3 разряда",
      "DAT_job": "Старшему специалисту 3 разряда"
    }
  },
  {
    "model": "Auth_LDAP.Jobs",
    "pk": 17,
    "fields": {
      "name": "Специалист 1 разряда",
      "sortBy": 17,
      "unique": "специалист1разряда",
      "RAD_job": "Специалиста 1 разряда",
      "DAT_job": "Специалисту 1 разряда"
    }
  },
  {
    "model": "Auth_LDAP.Jobs",
    "pk": 18,
    "fields": {
      "name": "Специалист 2 разряда",
      "sortBy": 18,
      "unique": "специалист2разряда",
      "RAD_job": "Специалиста 2 разряда",
      "DAT_job": "Специалисту 2 разряда"
    }
  },
  {
    "model": "Auth_LDAP.Jobs",
    "pk": 19,
    "fields": {
      "name": "Специалист 3 разряда",
      "sortBy": 19,
      "unique": "специалист3разряда",
      "RAD_job": "Специалиста 3 разряда",
      "DAT_job": "Специалисту 3 разряда"
    }
  },
  {
    "model": "Auth_LDAP.Jobs",
    "pk": 20,
    "fields": {
      "name": "Эксперт",
      "sortBy": 20,
      "unique": "эксперт",
      "RAD_job": "Эксперта",
      "DAT_job": "Эксперту"
    }
  }
]
